pybop_diffsol-0.1.2.dist-info/METADATA
pybop_diffsol-0.1.2.dist-info/WHEEL
pybop_diffsol/__init__.py
pybop_diffsol/pybop_diffsol.pyd
pybop_diffsol-0.1.2.dist-info/RECORD
